PopCatAPIWrapper/__init__.py
PopCatAPIWrapper/car_images.py
PopCatAPIWrapper/client.py
PopCatAPIWrapper/color.py
PopCatAPIWrapper/element.py
PopCatAPIWrapper/errors.py
PopCatAPIWrapper/film.py
PopCatAPIWrapper/http.py
PopCatAPIWrapper/meme.py
PopCatAPIWrapper/npm_package.py
PopCatAPIWrapper/showerthought.py
PopCatAPIWrapper/song.py
PopCatAPIWrapper/steamapp.py
PopCatAPIWrapper/subreddit.py
PopCatAPIWrapper/wyr.py
popcatapiwrapper-0.0.8.dist-info/LICENSE
popcatapiwrapper-0.0.8.dist-info/WHEEL
popcatapiwrapper-0.0.8.dist-info/METADATA
popcatapiwrapper-0.0.8.dist-info/RECORD
