Metadata-Version: 2.1
Name: popcatapiwrapper
Version: 0.0.8
Summary: PopCatWrapper is an asynchronous wrapper for https://popcat.xyz/api
Home-page: https://github.com/Infernum1/PopCatWrapper
License: MIT
Author: Infernum1
Requires-Python: >=3.10
Classifier: License :: OSI Approved :: MIT License
Classifier: Programming Language :: Python :: 3
Classifier: Programming Language :: Python :: 3.10
Requires-Dist: aiohttp (>=3.7.2,<4.0.0)
Requires-Dist: furo (>=2022.9.29,<2023.0.0)
Project-URL: Repository, https://github.com/Infernum1/PopCatWrapper
